mkdocssafetext/__init__.py
mkdocssafetext/config.py
mkdocssafetext/plugin.py
mkdocs_safe_text_plugin-1.6.1.dist-info/LICENSE
mkdocs_safe_text_plugin-1.6.1.dist-info/METADATA
mkdocs_safe_text_plugin-1.6.1.dist-info/WHEEL
mkdocs_safe_text_plugin-1.6.1.dist-info/entry_points.txt
mkdocs_safe_text_plugin-1.6.1.dist-info/top_level.txt
mkdocs_safe_text_plugin-1.6.1.dist-info/RECORD
