Metadata-Version: 2.1
Name: mkdocs-safe-text-plugin
Version: 1.6.1
Summary: Plugin for safe text editing with MKDocs.
Author-email: raimon <raimon49@hotmail.com>
License: BSD-2-Clause
Project-URL: Homepage, https://github.com/raimon49/mkdocs-safe-text-plugin
Project-URL: Releases, https://github.com/raimon49/mkdocs-safe-text-plugin/releases
Project-URL: Issues, https://github.com/raimon49/mkdocs-safe-text-plugin/issues
Project-URL: Changelog, https://github.com/raimon49/mkdocs-safe-text-plugin/blob/master/CHANGELOG.md
Keywords: mkdocs,bleach,xss
Classifier: Development Status :: 5 - Production/Stable
Classifier: License :: OSI Approved :: BSD License
Classifier: Programming Language :: Python
Classifier: Programming Language :: Python :: 3
Classifier: Programming Language :: Python :: 3 :: Only
Classifier: Programming Language :: Python :: 3.9
Classifier: Programming Language :: Python :: 3.10
Classifier: Programming Language :: Python :: 3.11
Classifier: Programming Language :: Python :: 3.12
Classifier: Topic :: Documentation
Classifier: Topic :: Text Processing
Requires-Python: >=3.9
License-File: LICENSE
Requires-Dist: bleach
Requires-Dist: bleach-allowlist >=1.0.3
Requires-Dist: mkdocs >=0.17.0
Provides-Extra: dev
Requires-Dist: autopep8 ; extra == 'dev'
Requires-Dist: docutils ; extra == 'dev'
Requires-Dist: wheel ; extra == 'dev'
Requires-Dist: pip-tools ; extra == 'dev'
Requires-Dist: pypandoc ; extra == 'dev'
Requires-Dist: pytest-cov ; extra == 'dev'
Requires-Dist: pytest-pycodestyle ; extra == 'dev'
Requires-Dist: pytest-runner ; extra == 'dev'
Requires-Dist: twine ; extra == 'dev'
